foliar-0.3.0.dist-info/METADATA
foliar-0.3.0.dist-info/WHEEL
foliar-0.3.0.dist-info/licenses/LICENSE
foliar/__init__.py
foliar/__init__.pyi
foliar/foliar.pypy311-pp73-x86_64-linux-gnu.so
foliar/py.typed
foliar-0.3.0.dist-info/RECORD
