Metadata-Version: 2.4
Name: foliar
Version: 0.3.0
Classifier: Programming Language :: Rust
Classifier: Programming Language :: Python :: Implementation :: CPython
Classifier: Programming Language :: Python :: Implementation :: PyPy
License-File: LICENSE
Summary: Foliar is a Rust-powered Python library for pretty-printing Python objects.
Keywords: rust,pyo3,pretty-printing
Author-email: Campbell Brown <campbellbrown093@gmail.com>
Requires-Python: >=3.8
Project-URL: homepage, https://github.com/campbellmbrown/foliar
Project-URL: source, https://github.com/campbellmbrown/foliar
Project-URL: issues, https://github.com/campbellmbrown/foliar/issues
